[
	{
		"id": 1,
		"name": "ICE",
		"description": "ICE raid",
		"fields": "[{\"id\":\"fa4683d9-a238-4884-8bb0-813169feea4f\",\"name\":\"size\",\"label\":\"Size\",\"type\":\"number\",\"required\":false,\"order\":0},{\"id\":\"db7f05a7-233e-438d-a34c-124e2ffdc852\",\"name\":\"activity\",\"label\":\"Activity\",\"type\":\"text\",\"required\":false,\"order\":1},{\"id\":\"7d656612-76a8-4808-bb5b-47c6fa5a790d\",\"name\":\"unit\",\"label\":\"Unit\",\"type\":\"text\",\"required\":false,\"order\":2},{\"id\":\"a7e32555-a821-4aba-8039-82bab193bd3d\",\"name\":\"equipment\",\"label\":\"Equipment\",\"type\":\"text\",\"required\":false,\"order\":3}]",
		"iconUrl": "/uploads/icons/15bbd076-e642-4a14-8334-d43c72a2393b.png",
		"createdAt": "2025-06-09 00:32:32.542",
		"updatedAt": "2025-06-09 00:32:42.484"
	},
	{
		"id": 2,
		"name": "Gas",
		"description": "Tear gas or other chemical weapons",
		"fields": "[{\"id\":\"3f2d8a94-3501-48f9-9bbf-468a4371ac9d\",\"name\":\"description\",\"label\":\"Description\",\"type\":\"text\",\"required\":false,\"order\":0}]",
		"iconUrl": "/uploads/icons/0848eafa-b665-4935-8700-d0f32e72c2c0.png",
		"createdAt": "2025-06-09 00:34:44.328",
		"updatedAt": "2025-06-09 00:34:52.93"
	},
	{
		"id": 3,
		"name": "Roadblock",
		"description": "",
		"fields": "[{\"id\":\"dba28de5-ef6d-486d-84ae-0f206384549d\",\"name\":\"unit\",\"label\":\"Unit\",\"type\":\"text\",\"required\":false,\"order\":0},{\"id\":\"6232a395-a9ce-4adf-840f-e57528c063f0\",\"name\":\"activity\",\"label\":\"Activity\",\"type\":\"text\",\"required\":false,\"order\":1}]",
		"iconUrl": "/uploads/icons/0e7de828-4a96-48b2-9490-834d5b792f85.png",
		"createdAt": "2025-06-09 00:35:43.789",
		"updatedAt": "2025-06-09 00:35:52.417"
	}
]